urbandictionaryapi/UrbanDictionary.py
urbandictionaryapi/__init__.py
urbandictionaryapi-1.1.0.dist-info/LICENSE
urbandictionaryapi-1.1.0.dist-info/METADATA
urbandictionaryapi-1.1.0.dist-info/WHEEL
urbandictionaryapi-1.1.0.dist-info/top_level.txt
urbandictionaryapi-1.1.0.dist-info/RECORD
